HTMLTableMaster/HTMLTable.py
HTMLTableMaster/__init__.py
HTMLTableMaster-0.0.1.dist-info/LICENSE
HTMLTableMaster-0.0.1.dist-info/METADATA
HTMLTableMaster-0.0.1.dist-info/WHEEL
HTMLTableMaster-0.0.1.dist-info/top_level.txt
HTMLTableMaster-0.0.1.dist-info/RECORD
