Metadata-Version: 2.1
Name: HTMLTableMaster
Version: 0.0.1
Summary: For scraping data from DPF
Home-page: https://github.com/Muditha-Rajapaksha-101/HTMLTableMaster.git
Author: Muditha Rajapaksha
Author-email: muditha.rajapaksha101@gmail.com
Classifier: Programming Language :: Python :: 3
Classifier: License :: OSI Approved :: MIT License
Classifier: Operating System :: OS Independent
Requires-Python: >=3.7
License-File: LICENSE
